{
    "Name":"temperature",
    "AutoValue":false,
    "Colors":[
        {"Value":0       ,"RGBA":"255,255,0,  0"  },
        {"Value":1       ,"RGBA":"0,  0,  214,200"},
        {"Value":10      ,"RGBA":"0,  5,  218,205"},
        {"Value":50      ,"RGBA":"0,  10, 222,210"},
        {"Value":100     ,"RGBA":"20, 70, 100,215"},
        {"Value":500     ,"RGBA":"50, 160,0,  220" },
        {"Value":1000    ,"RGBA":"60, 180,0,  225"  },
        {"Value":2000    ,"RGBA":"70, 200,0,  230"  },
        {"Value":3000    ,"RGBA":"100,230,0,  235" },
        {"Value":5000    ,"RGBA":"100,210,0,  240" },
        {"Value":6000    ,"RGBA":"100,200,0,  245" },
        {"Value":8000    ,"RGBA":"130,180,0,  250" },
        {"Value":10000   ,"RGBA":"150,200,0,  255" },
        {"Value":15000   ,"RGBA":"255,255,0,  255" },
        {"Value":20000   ,"RGBA":"255,200,0,  255" },
        {"Value":25000   ,"RGBA":"255,150,0,  255" },
        {"Value":30000   ,"RGBA":"255,100,0,  255" },
        {"Value":35000   ,"RGBA":"255,80, 0,  255"  },
        {"Value":40000   ,"RGBA":"255,40, 0,  255"  },
        {"Value":45000   ,"RGBA":"255,0,  0,  255"   },
        {"Value":50000   ,"RGBA":"250,10, 10, 255" },
        {"Value":60000   ,"RGBA":"240,20, 20, 255" },
        {"Value":70000   ,"RGBA":"230,30, 30, 255" },
        {"Value":100000  ,"RGBA":"220,40, 40, 255" },
        {"Value":200000  ,"RGBA":"210,40, 40, 255" },
        {"Value":300000  ,"RGBA":"200,40, 40, 255" },
        {"Value":400000  ,"RGBA":"190,40, 40, 255" },
        {"Value":500000  ,"RGBA":"180,40, 40, 255" },
        {"Value":600000  ,"RGBA":"170,40, 40, 255" },
        {"Value":700000  ,"RGBA":"160,40, 40, 255" },
        {"Value":800000  ,"RGBA":"150,40, 40, 255" }
    ]
}